README.txt
TODO.txt
setup.py
wc/__init__.py
wc.sqlrecipe.egg-info/PKG-INFO
wc.sqlrecipe.egg-info/SOURCES.txt
wc.sqlrecipe.egg-info/dependency_links.txt
wc.sqlrecipe.egg-info/namespace_packages.txt
wc.sqlrecipe.egg-info/not-zip-safe
wc.sqlrecipe.egg-info/requires.txt
wc.sqlrecipe.egg-info/top_level.txt
wc/sqlrecipe/__init__.py
wc/sqlrecipe/configure.zcml
wc/sqlrecipe/folder.py
wc/sqlrecipe/overrides.zcml
wc/sqlrecipe/recipe.py
