Metadata-Version: 1.0
Name: wc.sqlrecipe
Version: 3.8
Summary: SQL-based implementation of WorldCookery's Recipe content object
Home-page: http://worldcookery.com/Downloads
Author: Philipp von Weitershausen
Author-email: philipp@weitershausen.de
License: UNKNOWN
Platform: UNKNOWN
Classifier: Development Status :: 4 - Beta
Classifier: Framework :: Zope3
Classifier: Intended Audience :: Developers
